<!-- acronyms starting with D, see acronyms.xml for detail -->

<acrogroup tag="D">
  <acronym>
    <name>D</name>
    <meaning>document</meaning>
    <source/>
  </acronym>
  <acronym>
    <name>D&amp;E</name>
    <meaning>demonstration and
    evaluation programme</meaning>
    <source/>
  </acronym>
  <acronym>
    <name>D/L</name>
    <meaning>down link</meaning>
    <source>APD 04.05.03
    (95)04</source>
  </acronym>
  <acronym>
    <name>D-CAS</name>
    <meaning>digital channel
    associated signalling</meaning>
    <source/>
  </acronym>
  <acronym>
    <name>DA</name>
    <meaning>data
    administration</meaning>
    <source/>
  </acronym>
  <acronym>
    <name>DA</name>
    <meaning>Data
    Administrator</meaning>
    <source/>
  </acronym>
  <acronym>
    <name>DAA</name>
    <meaning>deployment
    assembly area</meaning>
    <source/>
  </acronym>
  <acronym>
    <name>DAB</name>
    <meaning>Dortmunder Aktien
    Brauerei</meaning>
    <source/>
  </acronym>
  <acronym>
    <name>DAC</name>
    <meaning>demodulator
    access controller</meaning>
    <source/>
  </acronym>
  <acronym>
    <name>DAC</name>
    <meaning>deployable ACCS
    component</meaning>
    <source/>
  </acronym>
  <acronym>
    <name>DAC</name>
    <meaning>discretionary
    access control</meaning>
    <source/>
  </acronym>
  <acronym>
    <name>DACAN</name>
    <meaning>distribution and
    accounting agency</meaning>
    <source>MC 108/5</source>
  </acronym>
  <acronym>
    <name>DAD</name>
    <meaning>demonstration
    architecture document</meaning>
    <source>STC CSNI final
    report 22/9/95</source>
  </acronym>
  <acronym>
    <name>DAD</name>
    <meaning>draft addendum</meaning>
    <source/>
  </acronym>
  <acronym>
    <name>DAMA</name>
    <meaning>demand assigned
    multiple access</meaning>
    <source>satellite
    communication</source>
  </acronym>
  <acronym>
    <name>DAMA</name>
    <meaning>demend assignment
    multiple access</meaning>
    <source>STC CSNI final
    report 22/9/95</source>
  </acronym>
  <acronym>
    <name>DAN</name>
    <meaning>depenses
    administratives nationales</meaning>
    <source/>
  </acronym>
  <acronym>
    <name>DAO</name>
    <meaning>Data
    Administration Organization</meaning>
    <source>ADSIA(ADP)-C-007-96</source>
  </acronym>
  <acronym>
    <name>DAO</name>
    <meaning>duty alerting
    officer</meaning>
    <source/>
  </acronym>
  <acronym>
    <name>DAP</name>
    <meaning>date achevement
    prevue</meaning>
    <source/>
  </acronym>
  <acronym>
    <name>DAP</name>
    <meaning>directory access
    protocol</meaning>
    <source/>
  </acronym>
  <acronym>
    <name>DARPA</name>
    <meaning>defense advanced
    research projects agancy</meaning>
    <source/>
  </acronym>
  <acronym>
    <name>DAT</name>
    <meaning>Digital Audio
    Tape</meaning>
    <source/>
  </acronym>
  <acronym>
    <name>Datex</name>
    <meaning>data exchange</meaning>
    <source/>
  </acronym>
  <acronym>
    <name>Datex-J</name>
    <meaning>data exchange
    f&uuml;r Jedermann</meaning>
    <source/>
  </acronym>
  <acronym>
    <name>DBA</name>
    <meaning>Database
    Administrator</meaning>
    <source/>
  </acronym>
  <acronym>
    <name>DBIWG</name>
    <meaning>database
    intelligence working group</meaning>
    <source/>
  </acronym>
  <acronym>
    <name>DBMS</name>
    <meaning>data base
    management system</meaning>
    <source/>
  </acronym>
  <acronym>
    <name>DCA</name>
    <meaning>defence
    communications agency</meaning>
    <source/>
  </acronym>
  <acronym>
    <name>DCA</name>
    <meaning>defensive counter
    air</meaning>
    <source/>
  </acronym>
  <acronym>
    <name>DCA</name>
    <meaning>dual capable A/C</meaning>
    <source/>
  </acronym>
  <acronym>
    <name>DCAOC</name>
    <meaning>deployable
    combined air operation centre</meaning>
    <source/>
  </acronym>
  <acronym>
    <name>DCC</name>
    <meaning>domain control
    centre</meaning>
    <source/>
  </acronym>
  <acronym>
    <name>DCDM</name>
    <meaning>digitally
    controlled delta modulation</meaning>
    <source/>
  </acronym>
  <acronym>
    <name>DCE</name>
    <meaning>data circuit
    equipment</meaning>
    <source>CCITT</source>
  </acronym>
  <acronym>
    <name>DCL</name>
    <meaning>description
    control language</meaning>
    <source/>
  </acronym>
  <acronym>
    <name>DCO</name>
    <meaning>duty
    communications officer</meaning>
    <source/>
  </acronym>
  <acronym>
    <name>DCOS</name>
    <meaning>deputy chief of
    staff</meaning>
    <source/>
  </acronym>
  <acronym>
    <name>DCP</name>
    <meaning>deployable
    command post</meaning>
    <source/>
  </acronym>
  <acronym>
    <name>DCS</name>
    <meaning>defence
    communications system</meaning>
    <source>US comm in Europe</source>
  </acronym>
  <acronym>
    <name>DCTS</name>
    <meaning>data
    communication terminal system</meaning>
    <source/>
  </acronym>
  <acronym>
    <name>DCW</name>
    <meaning>Digital Chart of
    the World</meaning>
    <source/>
  </acronym>
  <acronym>
    <name>DD</name>
    <meaning>draft document</meaning>
    <source/>
  </acronym>
  <acronym>
    <name>DDA</name>
    <meaning>domain-defined
    attribute</meaning>
    <source/>
  </acronym>
  <acronym>
    <name>DDC</name>
    <meaning>data display
    console</meaning>
    <source/>
  </acronym>
  <acronym>
    <name>DDF</name>
    <meaning>digital
    distribution frame</meaning>
    <source/>
  </acronym>
  <acronym>
    <name>DDG</name>
    <meaning>deputy director
    general</meaning>
    <source/>
  </acronym>
  <acronym>
    <name>DDI</name>
    <meaning>developing
    defence industries</meaning>
    <source/>
  </acronym>
  <acronym>
    <name>DDI</name>
    <meaning>Direct Dialing In</meaning>
    <source/>
  </acronym>
  <acronym>
    <name>DDL</name>
    <meaning>data definition
    language</meaning>
    <source/>
  </acronym>
  <acronym>
    <name>DDL</name>
    <meaning>digital data link</meaning>
    <source/>
  </acronym>
  <acronym>
    <name>DDN</name>
    <meaning>data directory
    number</meaning>
    <source/>
  </acronym>
  <acronym>
    <name>DDN</name>
    <meaning>defence data
    network</meaning>
    <source>US DOD</source>
  </acronym>
  <acronym>
    <name>DDN</name>
    <meaning>digital data
    network</meaning>
    <source/>
  </acronym>
  <acronym>
    <name>DEB</name>
    <meaning>digital European
    backbone</meaning>
    <source/>
  </acronym>
  <acronym>
    <name>DEC</name>
    <meaning>data exchange
    channel</meaning>
    <source/>
  </acronym>
  <acronym>
    <name>DEC</name>
    <meaning>derniere
    estimation de cout</meaning>
    <source/>
  </acronym>
  <acronym>
    <name>DEC</name>
    <meaning>Digital Equipment
    Corporation</meaning>
    <source/>
  </acronym>
  <acronym>
    <name>DECT</name>
    <meaning>digital European
    cordless communications</meaning>
    <source/>
  </acronym>
  <acronym>
    <name>DEE</name>
    <meaning>digital
    encryption equipment</meaning>
    <source/>
  </acronym>
  <acronym>
    <name>DEFS</name>
    <meaning>data encryption
    file system</meaning>
    <source>ACE ACCIS core
    cap specs</source>
  </acronym>
  <acronym>
    <name>DEKMS</name>
    <meaning>DACAN electronic
    key management system</meaning>
    <source/>
  </acronym>
  <acronym>
    <name>DEL</name>
    <meaning>direct exchange
    line</meaning>
    <source/>
  </acronym>
  <acronym>
    <name>DEP</name>
    <meaning>data exchange and
    processing</meaning>
    <source/>
  </acronym>
  <acronym>
    <name>DERA</name>
    <meaning>defense
    evaluation and research agency</meaning>
    <source>UK</source>
  </acronym>
  <acronym>
    <name>DERD</name>
    <meaning>Darstellung
    extrahierter Radar-Daten</meaning>
    <source/>
  </acronym>
  <acronym>
    <name>DES</name>
    <meaning>data encryption
    standard</meaning>
    <source/>
  </acronym>
  <acronym>
    <name>DF</name>
    <meaning>direction finding</meaning>
    <source/>
  </acronym>
  <acronym>
    <name>DF</name>
    <meaning>distribution
    frame</meaning>
    <source/>
  </acronym>
  <acronym>
    <name>DFC</name>
    <meaning>deputy financial
    controller</meaning>
    <source/>
  </acronym>
  <acronym>
    <name>DFD</name>
    <meaning>data fusion
    demonstrator</meaning>
    <source/>
  </acronym>
  <acronym>
    <name>DFTS</name>
    <meaning>defense fixed
    telecommunication system</meaning>
    <source>UK mil infra
    network</source>
  </acronym>
  <acronym>
    <name>DG</name>
    <meaning>defence guidance</meaning>
    <source/>
  </acronym>
  <acronym>
    <name>DG</name>
    <meaning>director general</meaning>
    <source/>
  </acronym>
  <acronym>
    <name>DG</name>
    <meaning>duty general</meaning>
    <source/>
  </acronym>
  <acronym>
    <name>DGIS</name>
    <meaning>digital graphic
    information service</meaning>
    <source>ACE ACCIS core
    cap specs</source>
  </acronym>
  <acronym>
    <name>DGNSS</name>
    <meaning>differntial
    global navigation satellite system</meaning>
    <source/>
  </acronym>
  <acronym>
    <name>DH</name>
    <meaning>dataflsh header</meaning>
    <source/>
  </acronym>
  <acronym>
    <name>DHD</name>
    <meaning>domain help desk</meaning>
    <source/>
  </acronym>
  <acronym>
    <name>DHDS</name>
    <meaning>data handling and
    display system</meaning>
    <source/>
  </acronym>
  <acronym>
    <name>DHRX</name>
    <meaning>digital
    hypothetical reference connection</meaning>
    <source/>
  </acronym>
  <acronym>
    <name>DHS</name>
    <meaning>document handling
    system</meaning>
    <source/>
  </acronym>
  <acronym>
    <name>DIA</name>
    <meaning>defence
    intelligence agency</meaning>
    <source>US project for
    DDN integration</source>
  </acronym>
  <acronym>
    <name>DID</name>
    <meaning>Direct Inawrd
    Dialling</meaning>
    <source/>
  </acronym>
  <acronym>
    <name>DIDS</name>
    <meaning>distribute
    intrusion detection system</meaning>
    <source/>
  </acronym>
  <acronym>
    <name>DIGEST</name>
    <meaning>digital
    geographic information exchange standard</meaning>
    <source/>
  </acronym>
  <acronym>
    <name>DIIS</name>
    <meaning>dedicated
    intelligence information system</meaning>
    <source/>
  </acronym>
  <acronym>
    <name>DILCS</name>
    <meaning>dedicated
    intelligence loop circuit system</meaning>
    <source/>
  </acronym>
  <acronym>
    <name>DIR</name>
    <meaning>Demonstration
    Issue Report</meaning>
    <source/>
  </acronym>
  <acronym>
    <name>DIR</name>
    <meaning>directorate</meaning>
    <source/>
  </acronym>
  <acronym>
    <name>DIR</name>
    <meaning>directory</meaning>
    <source/>
  </acronym>
  <acronym>
    <name>DIS</name>
    <meaning>defense
    information system</meaning>
    <source>life cycle
    methodology</source>
  </acronym>
  <acronym>
    <name>DIS</name>
    <meaning>distributed
    interactive simulation</meaning>
    <source/>
  </acronym>
  <acronym>
    <name>DIS</name>
    <meaning>draft
    international standard</meaning>
    <source>ISO</source>
  </acronym>
  <acronym>
    <name>DISA</name>
    <meaning>defense
    information systems agency</meaning>
    <source/>
  </acronym>
  <acronym>
    <name>DISBEE</name>
    <meaning>digital
    intermediate speed bulk encryption equipment</meaning>
    <source/>
  </acronym>
  <acronym>
    <name>DISNET</name>
    <meaning>defence
    integrated secure network</meaning>
    <source/>
  </acronym>
  <acronym>
    <name>DISTAFF</name>
    <meaning>directing staff</meaning>
    <source/>
  </acronym>
  <acronym>
    <name>DISTEL</name>
    <meaning>digitales
    Info-System f&uuml;r taktische Einsatzzentralen der Luftwaffe</meaning>
    <source/>
  </acronym>

  <acronym>
    <name>DIT</name>
    <meaning>directory
    information tree</meaning>
    <source/>
  </acronym>
  <acronym>
    <name>DITSN</name>
    <meaning>digital Italian
    Tri-Service network</meaning>
    <source/>
  </acronym>
  <acronym>
    <name>DL</name>
    <meaning>data link</meaning>
    <source/>
  </acronym>
  <acronym>
    <name>DLCP</name>
    <meaning>data link change
    proposal</meaning>
    <source/>
  </acronym>
  <acronym>
    <name>DLCU</name>
    <meaning>data link control
    unit</meaning>
    <source/>
  </acronym>
  <acronym>
    <name>DLE</name>
    <meaning>defeat the lead
    echelon</meaning>
    <source/>
  </acronym>
  <acronym>
    <name>DLP</name>
    <meaning>data link
    procedure</meaning>
    <source/>
  </acronym>
  <acronym>
    <name>DLP</name>
    <meaning>data link
    protocol</meaning>
    <source/>
  </acronym>
  <acronym>
    <name>DLS</name>
    <meaning>data link service</meaning>
    <source/>
  </acronym>
  <acronym>
    <name>DLT</name>
    <meaning>data link
    terminal</meaning>
    <source/>
  </acronym>
  <acronym>
    <name>DLWG</name>
    <meaning>data link working
    group</meaning>
    <source/>
  </acronym>
  <acronym>
    <name>DM</name>
    <meaning>data management</meaning>
    <source/>
  </acronym>
  <acronym>
    <name>DMA</name>
    <meaning>Defence Mapping
    Agency</meaning>
    <source/>
  </acronym>
  <acronym>
    <name>DMA</name>
    <meaning>direct memory
    access</meaning>
    <source/>
  </acronym>
  <acronym>
    <name>DME</name>
    <meaning>distance
    measuring equipment</meaning>
    <source/>
  </acronym>
  <acronym>
    <name>DME</name>
    <meaning>distributed
    management environment</meaning>
    <source/>
  </acronym>
  <acronym>
    <name>DML</name>
    <meaning>data manipulation
    language</meaning>
    <source/>
  </acronym>
  <acronym>
    <name>DMP</name>
    <meaning>data
    multi-processor</meaning>
    <source>mode S</source>
  </acronym>
  <acronym>
    <name>DMS</name>
    <meaning>defence
    management system</meaning>
    <source>US project for
    DDN integration</source>
  </acronym>
  <acronym>
    <name>DMS</name>
    <meaning>defence message
    system</meaning>
    <source>AC/317-N/833</source>
  </acronym>
  <acronym>
    <name>DNA</name>
    <meaning>Defence Nuclear
    Agency</meaning>
    <source/>
  </acronym>
  <acronym>
    <name>DNI</name>
    <meaning>Digital NATO
    Interface</meaning>
    <source/>
  </acronym>
  <acronym>
    <name>DNS</name>
    <meaning>Direct NICS
    Subscriber</meaning>
    <source>NACISA/APD/04.07.00(95)001</source>
  </acronym>
  <acronym>
    <name>DNS</name>
    <meaning>domain name
    server</meaning>
    <source>STC CSNI final
    report 22/9/95</source>
  </acronym>
  <acronym>
    <name>DNS</name>
    <meaning>dynamic name
    service</meaning>
    <source>Ex Strong Resolve
    95</source>
  </acronym>
  <acronym>
    <name>DNSP</name>
    <meaning>draft NATO
    standardised profile</meaning>
    <source/>
  </acronym>
  <acronym>
    <name>DOB</name>
    <meaning>dispersed
    operating base</meaning>
    <source/>
  </acronym>
  <acronym>
    <name>DOBS</name>
    <meaning>DISTAFF order of
    battle system</meaning>
    <source/>
  </acronym>
  <acronym>
    <name>DOD</name>
    <meaning>department of
    defense</meaning>
    <source/>
  </acronym>
  <acronym>
    <name>DOI</name>
    <meaning>department of
    industry</meaning>
    <source/>
  </acronym>
  <acronym>
    <name>DOL</name>
    <meaning>deployed
    operations location</meaning>
    <source>APD 04.05.03
    (95)04</source>
  </acronym>
  <acronym>
    <name>DOL</name>
    <meaning>dispersed
    operating location</meaning>
    <source/>
  </acronym>
  <acronym>
    <name>DOLCE</name>
    <meaning>Digital On-line
    Crypto Equipment</meaning>
    <source/>
  </acronym>
  <acronym>
    <name>DOP</name>
    <meaning>director of
    operations</meaning>
    <source/>
  </acronym>
  <acronym>
    <name>DoS</name>
    <meaning>Denial of Service</meaning>
    <source/>
  </acronym>
  <acronym>
    <name>DOS</name>
    <meaning>director of
    support</meaning>
    <source/>
  </acronym>
  <acronym>
    <name>DP</name>
    <meaning>draft proposal</meaning>
    <source/>
  </acronym>
  <acronym>
    <name>DPA</name>
    <meaning>Dayton peace
    agreement</meaning>
    <source/>
  </acronym>
  <acronym>
    <name>DPC</name>
    <meaning>Defense Planning
    Council</meaning>
    <source>APD 04.05.03
    (95)04</source>
  </acronym>
  <acronym>
    <name>DPDA</name>
    <meaning>date prevue de
    demande d&apos;autorisation</meaning>
    <source>EDAR</source>
  </acronym>
  <acronym>
    <name>DPDS</name>
    <meaning>data processing
    distribution system</meaning>
    <source/>
  </acronym>
  <acronym>
    <name>DPNSS</name>
    <meaning>Digital Private
    Network Signalling System</meaning>
    <source/>
  </acronym>
  <acronym>
    <name>DPP</name>
    <meaning>defence planning
    and policy division</meaning>
    <source>NATO IS division</source>
  </acronym>
  <acronym>
    <name>DPQ</name>
    <meaning>defense planning
    questionnaire</meaning>
    <source/>
  </acronym>
  <acronym>
    <name>DPSK</name>
    <meaning>differential
    phase shift keyed</meaning>
    <source/>
  </acronym>
  <acronym>
    <name>DQDB</name>
    <meaning>distributed queue
    dual bus</meaning>
    <source/>
  </acronym>
  <acronym>
    <name>DRA</name>
    <meaning>defense research
    agency</meaning>
    <source>UK</source>
  </acronym>
  <acronym>
    <name>DRAS</name>
    <meaning>DFS reply
    analysis system</meaning>
    <source/>
  </acronym>
  <acronym>
    <name>DRC</name>
    <meaning>Defence Review
    Committee</meaning>
    <source/>
  </acronym>
  <acronym>
    <name>DRG</name>
    <meaning>defence research
    group</meaning>
    <source/>
  </acronym>
  <acronym>
    <name>DRR</name>
    <meaning>Defense
    Requirements Review</meaning>
    <source/>
  </acronym>
  <acronym>
    <name>DRS</name>
    <meaning>draft requirement
    statement</meaning>
    <source/>
  </acronym>
  <acronym>
    <name>DS</name>
    <meaning>decision sheet</meaning>
    <source/>
  </acronym>
  <acronym>
    <name>DS</name>
    <meaning>Defense Support
    Division</meaning>
    <source>NATO IS division</source>
  </acronym>
  <acronym>
    <name>DS</name>
    <meaning>directory
    services</meaning>
    <source/>
  </acronym>
  <acronym>
    <name>DS</name>
    <meaning>draft STANAG</meaning>
    <source/>
  </acronym>
  <acronym>
    <name>DSA</name>
    <meaning>defense shipping
    agency</meaning>
    <source/>
  </acronym>
  <acronym>
    <name>DSA</name>
    <meaning>directory service
    agent</meaning>
    <source>AC/317-N/846</source>
  </acronym>
  <acronym>
    <name>DSA</name>
    <meaning>directory system
    agent</meaning>
    <source>AC/317-N/846</source>
  </acronym>
  <acronym>
    <name>DSATS</name>
    <meaning>Digital SHAPE
    Area Transmission System</meaning>
    <source/>
  </acronym>
  <acronym>
    <name>DSCS</name>
    <meaning>Defense Satellite
    Communications System (US)</meaning>
    <source>STC CSNI final
    report 22/9/95</source>
  </acronym>
  <acronym>
    <name>DSE</name>
    <meaning>Data Switching
    Equipment</meaning>
    <source/>
  </acronym>
  <acronym>
    <name>DSF</name>
    <meaning>depoyed SHED
    facility</meaning>
    <source/>
  </acronym>
  <acronym>
    <name>DSN</name>
    <meaning>Defense Switched
    Network</meaning>
    <source/>
  </acronym>
  <acronym>
    <name>DSN</name>
    <meaning>digital switched
    network</meaning>
    <source/>
  </acronym>
  <acronym>
    <name>DSP</name>
    <meaning>directory system
    protocol</meaning>
    <source/>
  </acronym>
  <acronym>
    <name>DSP</name>
    <meaning>domain specific
    part</meaning>
    <source/>
  </acronym>
  <acronym>
    <name>DSS</name>
    <meaning>data server
    system</meaning>
    <source/>
  </acronym>
  <acronym>
    <name>DSS</name>
    <meaning>digital signature
    standard</meaning>
    <source/>
  </acronym>
  <acronym>
    <name>DSSS</name>
    <meaning>direct sequence
    spread spectrum</meaning>
    <source/>
  </acronym>
  <acronym>
    <name>DSSSL</name>
    <meaning>document style
    semantics and specification language</meaning>
    <source/>
  </acronym>
  <acronym>
    <name>DST</name>
    <meaning>decision support
    tools</meaning>
    <source/>
  </acronym>
  <acronym>
    <name>DTA</name>
    <meaning>division
    technical advisor</meaning>
    <source/>
  </acronym>
  <acronym>
    <name>DTBR</name>
    <meaning>down time before
    repair</meaning>
    <source>ACE ACCIS core
    cap specs</source>
  </acronym>
  <acronym>
    <name>DTC</name>
    <meaning>department of
    trade and commerce</meaning>
    <source/>
  </acronym>
  <acronym>
    <name>DTD</name>
    <meaning>data transfer
    device</meaning>
    <source/>
  </acronym>
  <acronym>
    <name>DTD</name>
    <meaning>document type
    definition</meaning>
    <source>ACE ACCIS core
    cap specs</source>
  </acronym>
  <acronym>
    <name>DTE</name>
    <meaning>data terminal
    equipment</meaning>
    <source/>
  </acronym>
  <acronym>
    <name>DTE</name>
    <meaning>data terminating
    equipment</meaning>
    <source>CCITT</source>
  </acronym>
  <acronym>
    <name>DTED</name>
    <meaning>digital terrain
    evaluation data</meaning>
    <source>ACE ACCIS core
    cap specs</source>
  </acronym>
  <acronym>
    <name>DTL</name>
    <meaning>Daily Target List</meaning>
    <source/>
  </acronym>
  <acronym>
    <name>DTMP</name>
    <meaning>data comm.
    protocol standards technical managem. panel</meaning>
    <source/>
  </acronym>
  <acronym>
    <name>DTR</name>
    <meaning>draft technical
    report</meaning>
    <source/>
  </acronym>
  <acronym>
    <name>DTS</name>
    <meaning>data terminal set</meaning>
    <source/>
  </acronym>
  <acronym>
    <name>DU</name>
    <meaning>dial up</meaning>
    <source/>
  </acronym>
  <acronym>
    <name>DUA</name>
    <meaning>directory user
    agent</meaning>
    <source/>
  </acronym>
  <acronym>
    <name>DUSS</name>
    <meaning>data unit
    specific software</meaning>
    <source/>
  </acronym>
  <acronym>
    <name>D&Uuml;V</name>
    <meaning>Daten&uuml;bertragungs-
    und -vermittlungssystem</meaning>
    <source/>
  </acronym>
  <acronym>
    <name>DVITS</name>
    <meaning>digital video
    image transmission system</meaning>
    <source/>
  </acronym>
  <acronym>
    <name>DWS</name>
    <meaning>distributed
    wargaming system</meaning>
    <source/>
  </acronym>
  <acronym>
    <name>DXS</name>
    <meaning>digital
    cross-connect</meaning>
    <source/>
  </acronym>
</acrogroup>

