<?xml version="1.0" encoding="utf-8"?>
<!DOCTYPE appendix PUBLIC "-//OASIS//DTD DocBook XML V4.5//EN" "../schema/dtd/docbkx45/docbookx.dtd"[
<!ENTITY nisp-web-mainpage "http://nisp.nc3a.nato.int/">
]>
<appendix
 id="v1-ChangeLog">
  <!--
 *****************************************************************
       Annex - Detailed Record of Changes
 *****************************************************************
-->
    <title>Detailed Changes from NISP Version 9 (I) to NISP Version 10 (J)</title>

<sect1>
  <title>Changes to documents</title>


<table frame="all" id="v1c-changes">
            <title>Change Log</title>
            <tgroup
              align="left"
              cols="7">
              <colspec colwidth="10*" colname="c1"/>
              <colspec colwidth="10*" colname="c2"/>
              <colspec colwidth="10*" colname="c3"/>
              <colspec colwidth="13*" colname="c4"/>
              <colspec colwidth="30*" colname="c5"/>
              <colspec colwidth="10*" colname="c6"/>
              <colspec colwidth="17*" colname="c7"/>
              <thead>
                <row>
                  <entry>Type<footnote><para><emphasis role="bold">Types - A</emphasis>: Addition; <emphasis role="bold">D</emphasis>: Deletion;<emphasis role="bold"> U</emphasis>: Updated; <emphasis role="bold">E</emphasis>: Errata correction</para></footnote>
</entry>
                  <entry>Edition</entry>
                  <entry>Volume</entry>
                  <entry>Section,Paragraph,etc.</entry>
                  <entry>Description</entry>
                  <entry>RFCP</entry>
                  <entry>Remarks</entry>
                </row>
              </thead>
              <tbody>
		<row>
                  <entry>U</entry>
                  <entry>I</entry>
                  <entry>1</entry>
                  <entry>Introduction</entry>
                  <entry>Updated footnote</entry>
                  <entry></entry>
                  <entry></entry>
                </row>
		<row>
                  <entry>D</entry>
                  <entry>3</entry>
                  <entry>Annex</entry>
                  <entry>B to H</entry>
                  <entry>All profiles now hyperlinked baseline documents</entry>
                  <entry></entry>
                  <entry></entry>
                </row>
		<row>
                  <entry>U</entry>
                  <entry>2,3</entry>
                  <entry>Annex</entry>
                  <entry>A</entry>
                  <entry>Updated to reference profiles using hyperlinks</entry>
                  <entry></entry>
                  <entry></entry>
                </row>
		<row>
                  <entry>A</entry>
                  <entry>J</entry>
                  <entry>2</entry>
                  <entry>Profile</entry>
                  <entry>Added 14 Metadata Binding Profiles</entry>
                  <entry>9-002</entry>
                  <entry></entry>
                </row>
		<row>
                  <entry>A</entry>
                  <entry>J</entry>
                  <entry>2</entry>
                  <entry>Standards</entry>
                  <entry>IETF RFC 7208,7321,7619,4253,2484</entry>
                  <entry>9-012</entry>
                  <entry></entry>
                </row>
		<row>
                  <entry>U</entry>
                  <entry>J</entry>
                  <entry>2</entry>
                  <entry>Standards</entry>
                  <entry>NIST FIPS 180-4,186-4</entry>
                  <entry>9-012</entry>
                  <entry></entry>
                </row>
		<row>
                  <entry>D</entry>
                  <entry>J</entry>
                  <entry>2</entry>
                  <entry>Standards</entry>
                  <entry>IEEE P802.10a,b,c,d; IETF RFC 1828, 2403, 2404, 2405, 2408, 4835</entry>
                  <entry>9-012</entry>
                  <entry></entry>
                </row>
		<row>
                  <entry>U</entry>
                  <entry>J</entry>
                  <entry>2</entry>
                  <entry>Standards</entry>
                  <entry>Updated Responsible Parties</entry>
                  <entry>9-013, 9-014, 9-017, 9-019</entry>
                  <entry></entry>
                </row>
		<row>
                  <entry>A</entry>
                  <entry>J</entry>
                  <entry>2</entry>
                  <entry>Profiles</entry>
                  <entry>Added AI TECH SIPS 06.02.01 thru 06.02.14</entry>
                  <entry>9-015</entry>
                  <entry></entry>
                </row>
		<row>
                  <entry>A</entry>
                  <entry>J</entry>
                  <entry>2</entry>
                  <entry>Standards</entry>
                  <entry>103 new standards to Vol 2 of the NISP</entry>
                  <entry>9-016</entry>
                  <entry></entry>
                </row>
		<row>
                  <entry>D</entry>
                  <entry>J</entry>
                  <entry>2</entry>
                  <entry>Standards</entry>
                  <entry>STANAG 4339, 5059 ed.1/Amd2, 4175 Ed.4, 4271 Ed.1, 4376 Ed.1, 4421, 4484 Ed.2, 4485 Ed.1, 4486 Ed.2, 4492 Ed.2, 4505 Ed.1, 4577 Ed.1, 4484 (Draft), 4606 Ed.1, 5501 Ed.5, 5501 Ed.6, 5511 Ed.5, 5514 Ed.2, 5602 Ed.3</entry>
                  <entry>9-016</entry>
                  <entry></entry>
                </row>
		<row>
                  <entry>A</entry>
                  <entry>J</entry>
                  <entry>3</entry>
                  <entry>Standards</entry>
                  <entry>20 new standards to Vol 3 of the NISP</entry>
                  <entry>9-016</entry>
                  <entry></entry>
                </row>
		<row>
                  <entry>U</entry>
                  <entry>J</entry>
                  <entry>2,3</entry>
                  <entry>Standards</entry>
                  <entry>Move STANAG 4559 Ed.4 from Volume 2 to Volume 3</entry>
                  <entry>9-018</entry>
                  <entry></entry>
                </row>
		<row>
                  <entry>A</entry>
                  <entry>J</entry>
                  <entry>2</entry>
                  <entry>Standards</entry>
                  <entry>Add RTF Specification, Version 1.9.1;IETF RFC 7230, 5689, 6854, 2228, 2640, 2773, 3659, 5797, 7151</entry>
                  <entry>9-018</entry>
                  <entry></entry>
                </row>
		<row>
                  <entry>A</entry>
                  <entry>J</entry>
                  <entry>3</entry>
                  <entry>Standards</entry>
                  <entry>Bluetooth 4.2;WS-I Basic Profile 1.2;Common Alerting Protocol Version 1.2;</entry>
                  <entry>9-018</entry>
                  <entry></entry>
                </row>
		<row>
                  <entry>A</entry>
                  <entry>J</entry>
                  <entry>3</entry>
                  <entry>Standards</entry>
                  <entry>NATO Interoperability Standards and Profiles eXchange Specification</entry>
                  <entry>9-020</entry>
                  <entry>AC/322-WP(2016)0082</entry>
                </row>
		<row>
                  <entry>U</entry>
                  <entry>J</entry>
                  <entry>3</entry>
                  <entry>Standards</entry>
                  <entry>TMForum REST Specifications TMF621 R14.4.1 V1.3.5; TMF622, R14.5.1 V2.0.1; TR250 R15.5.1 V2.0.1</entry>
                  <entry>20160919-001</entry>
                  <entry></entry>
                </row>
		<row>
                  <entry>U</entry>
                  <entry>J</entry>
                  <entry>2</entry>
                  <entry>Standards</entry>
                  <entry>BPML update to Version 2.0.2</entry>
                  <entry>20161110-001</entry>
                  <entry></entry>
                </row>
		<row>
                  <entry>A</entry>
                  <entry>J</entry>
                  <entry>3</entry>
                  <entry>Profile</entry>
                  <entry>Proposed FMN Spiral 2 Standards Profile</entry>
                  <entry>20161115-001</entry>
                  <entry></entry>
                </row>
		<row>
                  <entry>A</entry>
                  <entry>J</entry>
                  <entry>3</entry>
                  <entry>Standard</entry>
                  <entry>ISO/IEC/IEEE 42010:2011; ISO/IEC/IEEE 42020</entry>
                  <entry>20161110-002</entry>
                  <entry></entry>
                </row>
		<row>
                  <entry>A</entry>
                  <entry>J</entry>
                  <entry>2</entry>
                  <entry>Standard</entry>
                  <entry>ISO/IEC 19794-14:2013</entry>
                  <entry>20161110-003</entry>
                  <entry></entry>
                </row>
		<row>
                  <entry>A</entry>
                  <entry>J</entry>
                  <entry>2</entry>
                  <entry>Standard</entry>
                  <entry>OGC Web Services Common Implementation Specification, v2.0.0, 06-121r9, 2010-04-07; Corrigendum 1 for OGC Web Services Common Standard v2.0.0 – Multilingual, 11-157, 2011-10-18 ;OGC Styled Layer Descriptor (SLD) Implementation Specification v1.0.0, 02-070, 2002-09-19</entry>
                  <entry>20161116-001</entry>
                  <entry></entry>
                </row>
		<row>
                  <entry>A</entry>
                  <entry>J</entry>
                  <entry>3</entry>
                  <entry>Standard</entry>
                  <entry>OMG SoaML Version 1.0.1</entry>
                  <entry>20161110-004</entry>
                  <entry></entry>
                </row>
		<row>
                  <entry>A</entry>
                  <entry>J</entry>
                  <entry>3</entry>
                  <entry>Standard</entry>
                  <entry>OMG SysML Version 1.4</entry>
                  <entry>20161110-005</entry>
                  <entry></entry>
                </row>
              </tbody>
            </tgroup>
          </table>

</sect1>


<sect1 id="new-standards">
  <title>New standards</title>
  <sect2 id="bluetooth-sig">
    <title>Bluetooth SIG</title>
    <itemizedlist spacing="compact">
      <listitem>
        <para>
          Bluetooth 4.2 (Bluetooth SIG bluetooth42:2014)
        </para>
      </listitem>
    </itemizedlist>
  </sect2>
  <sect2 id="c3b-cap1">
    <title>C3B CaP/1</title>
    <itemizedlist spacing="compact">
      <listitem>
        <para>
          Web Service Messaging Profile (WSMP) (C3B CaP/1 :2016)
        </para>
      </listitem>
    </itemizedlist>
  </sect2>
  <sect2 id="cceb">
    <title>CCEB</title>
    <itemizedlist spacing="compact">
      <listitem>
        <para>
          Allied Call Sign and Address Group System - Instructions and
          Assignments (CCEB ACP 100 (F))
        </para>
      </listitem>
      <listitem>
        <para>
          Call Sign Book for Ships (CCEB ACP 113 (AD))
        </para>
      </listitem>
      <listitem>
        <para>
          Call Sign Book for Ships (CCEB ACP 113 (AJ))
        </para>
      </listitem>
      <listitem>
        <para>
          Allied Routing Indicator Book (CCEB ACP 117 (K))
        </para>
      </listitem>
      <listitem>
        <para>
          Allied Routing Indicator Book (CCEB ACP 117 (O))
        </para>
      </listitem>
      <listitem>
        <para>
          Comms Instructions - General (CCEB ACP 121 (I))
        </para>
      </listitem>
      <listitem>
        <para>
          Information Assurance for Allied Communications and
          Information Systems (CCEB ACP 122 (D))
        </para>
      </listitem>
      <listitem>
        <para>
          Information Assurance for Allied Communications and
          Information Systems (CCEB ACP 122 (G))
        </para>
      </listitem>
      <listitem>
        <para>
          Communication Instructions - Signaling Procedures in the
          Visual Medium (CCEB ACP 130 (A))
        </para>
      </listitem>
      <listitem>
        <para>
          Communication Instructions - Operating Signals (CCEB ACP 131
          (F))
        </para>
      </listitem>
      <listitem>
        <para>
          Communication Instructions - Distress and Rescue Procedures
          (CCEB ACP 135 (F))
        </para>
      </listitem>
      <listitem>
        <para>
          IFF/SIF Operational Procedures (CCEB ACP 160 (E))
        </para>
      </listitem>
      <listitem>
        <para>
          Glossary of C-E Terms (CCEB ACP 167 (G))
        </para>
      </listitem>
      <listitem>
        <para>
          Glossary of C-E Terms (CCEB ACP 167 (K))
        </para>
      </listitem>
      <listitem>
        <para>
          Guide to Spectrum Management in Military Operations (CCEB ACP
          190 (A))
        </para>
      </listitem>
      <listitem>
        <para>
          Instructions for the Preparation of ACPs (CCEB ACP 198 (N))
        </para>
      </listitem>
      <listitem>
        <para>
          Mobile Tactical Wide Area Networking (MTWAN) in the Maritime
          Environment - Operating Guidance (CCEB ACP 200 V1 (D))
        </para>
      </listitem>
      <listitem>
        <para>
          Mobile Tactical Wide Area Networking (MTWAN) Technical
          Instructions (CCEB ACP 200 V2 (C) )
        </para>
      </listitem>
      <listitem>
        <para>
          Mobile Tactical Wide Area Networking (MTWAN) Technical
          Instructions (CCEB ACP 200 V2 (D) )
        </para>
      </listitem>
      <listitem>
        <para>
          Communications Instructions Internet Protocol (IP) Services
          (CCEB ACP 201 (Orig))
        </para>
      </listitem>
    </itemizedlist>
  </sect2>
  <sect2 id="ietf">
    <title>IETF</title>
    <itemizedlist spacing="compact">
      <listitem>
        <para>
          An Aplication of the BGP Community Attribute in Multi-Home
          Routing (IETF RFC 1998)
        </para>
      </listitem>
      <listitem>
        <para>
          FTP Security Extensions (IETF RFC 2228:1997)
        </para>
      </listitem>
      <listitem>
        <para>
          PPP LCP Internationalization Configuration Option (IETF RFC
          2484:1999)
        </para>
      </listitem>
      <listitem>
        <para>
          Internationalization of the File Transfer Protocol (IETF RFC
          2640:1999)
        </para>
      </listitem>
      <listitem>
        <para>
          Encryption using KEA and SKIPJACK (IETF RFC 2773:2000)
        </para>
      </listitem>
      <listitem>
        <para>
          A Flexible Method for Managing the Assignment of Bits of an
          IPv6 Address Block (IETF RFC 3531:2003)
        </para>
      </listitem>
      <listitem>
        <para>
          Extensions to FTP (IETF RFC 3659:2007)
        </para>
      </listitem>
      <listitem>
        <para>
          The Secure Shell (SSH) Transport Layer Protocol (IETF RFC
          4253:2006)
        </para>
      </listitem>
      <listitem>
        <para>
          Considerations for Internet group Management protocols (IGMP)
          and Multicast listener Discovery Snooping Switches (IETF RFC
          4541:2006)
        </para>
      </listitem>
      <listitem>
        <para>
          IPv6 Stateless Address Autoconfiguration (IETF RFC 4862:2007)
        </para>
      </listitem>
      <listitem>
        <para>
          Extended MKCOL for Web Distributed Authoring and Versioning
          (WebDAV) (IETF RFC 5689:2009)
        </para>
      </listitem>
      <listitem>
        <para>
          FTP Command and Extension Registry (IETF RFC 5797:2010)
        </para>
      </listitem>
      <listitem>
        <para>
          Update to Internet Message Format to Allow Group Syntax in the
          &quot;From:&quot; and &quot;Sender:&quot; Header Fields (IETF
          RFC 6854:2013)
        </para>
      </listitem>
      <listitem>
        <para>
          File Transfer Protocol HOST Command for Virtual Hosts (IETF
          RFC 7151:2014)
        </para>
      </listitem>
      <listitem>
        <para>
          Sender Policy Framework (SPF) for Authorizing Use of Domains
          in Email, Version 1 (IETF RFC 7208:2014)
        </para>
      </listitem>
      <listitem>
        <para>
          Hypertext Transfer Protocol (HTTP/1.1): Message Syntax and
          Routing (IETF RFC 7230:2014)
        </para>
      </listitem>
      <listitem>
        <para>
          Cryptographic Algorithm Implementation Requirements and Usage
          Guidance for Encapsulating Security Payload (ESP) and
          Authentication Header (AH) (IETF RFC 7321:2014)
        </para>
      </listitem>
      <listitem>
        <para>
          The NULL Authentication Method in the Internet Key Exchange
          Protocol Version 2 (IKEv2) (IETF RFC 7619:2015)
        </para>
      </listitem>
    </itemizedlist>
  </sect2>
  <sect2 id="iicwg">
    <title>IICWG</title>
    <itemizedlist spacing="compact">
      <listitem>
        <para>
          NATO Elliptic Curve (EC) Key Material Specification Rev. 1.0.
          (IICWG SCIP-233.102)
        </para>
      </listitem>
      <listitem>
        <para>
          NATO Pre Placed Key (PPK) Key Material Format and Fill Checks
          Specification Rev.1.0 (IICWG SCIP-233.104)
        </para>
      </listitem>
      <listitem>
        <para>
          Universal Elliptic Curve (EC) Key Material Specification Rev.
          1.0 (IICWG SCIP-233.105)
        </para>
      </listitem>
      <listitem>
        <para>
          Universal Multi-Point Pre Placed Key (PPK) Material Format and
          Fill Specification Rev. 1.0 (IICWG SCIP-233.108)
        </para>
      </listitem>
      <listitem>
        <para>
          Unencrypted Key Fill Specification Rev. 1.0. (IICWG
          SCIP-233.150)
        </para>
      </listitem>
      <listitem>
        <para>
          CRC Calculations Specifications Rev. 1.0. (IICWG SCIP-233.151)
        </para>
      </listitem>
      <listitem>
        <para>
          Universal Call-Setup Encryption (CSE) Specification Rev. 1.0.
          (IICWG SCIP-233.201)
        </para>
      </listitem>
      <listitem>
        <para>
          NATO EC Agreement and TEK Derivation Specification Rev. 1.0.
          (IICWG SCIP-233.302)
        </para>
      </listitem>
      <listitem>
        <para>
          Universal ECMQV Key Agreement and TEK Derivation Specification
          Rev. 1.0 (IICWG SCIP-233.303)
        </para>
      </listitem>
      <listitem>
        <para>
          NATO Point-to-Point and Multipoint PPK-Processing
          Specification Rev.1.0 (IICWG SCIP-233.304)
        </para>
      </listitem>
      <listitem>
        <para>
          Universal Multipoint PPK-Processing Specification Rev. 1.0.
          (IICWG SCIP-233.305)
        </para>
      </listitem>
      <listitem>
        <para>
          Call Set-Up encryption (CSE) State Vector Processing
          Specification Rev. 1.0. (IICWG SCIP-233.402)
        </para>
      </listitem>
      <listitem>
        <para>
          NATO Fixed Filler Generation Specification Rev. 1.0. (IICWG
          SCIP-233.422)
        </para>
      </listitem>
      <listitem>
        <para>
          Universal Fixed Filler Generation Specification Rev. 1.0.
          (IICWG SCIP-233.423)
        </para>
      </listitem>
      <listitem>
        <para>
          Point-to-Point Cryptographic Verification Specification Rev.
          1.1. (IICWG SCIP-233.441)
        </para>
      </listitem>
      <listitem>
        <para>
          Multipoint Cryptographic Verification Specification Rev. 1.0.
          (IICWG SCIP-233.442)
        </para>
      </listitem>
      <listitem>
        <para>
          Point-to-Point Cryptographic verification W/HMAC Specification
          Rev. 1.0. (IICWG SCIP-233.443)
        </para>
      </listitem>
      <listitem>
        <para>
          Secure G.729D Voice Specification Rev. 1.1. (IICWG
          SCIP-233.502)
        </para>
      </listitem>
      <listitem>
        <para>
          Secure Reliable Transport (RT) Asynchronous Data Specification
          Rev. 1.1. (IICWG SCIP-233.516)
        </para>
      </listitem>
      <listitem>
        <para>
          Secuer Best effort Transport (BET) Asynchronous Data Transfer
          Rev. 1.1. (IICWG SCIP-233.517)
        </para>
      </listitem>
      <listitem>
        <para>
          Secure Dial Processing Specification Rev. 1.1. (IICWG
          SCIP-233.546)
        </para>
      </listitem>
      <listitem>
        <para>
          MONGOOSE Encryption Algorithm Specification Rev. 1.0. (IICWG
          SCIP-233.563)
        </para>
      </listitem>
      <listitem>
        <para>
          AES-256 Encryption Algorithm Specification Rev. 1.0. (IICWG
          SCIP-233.601)
        </para>
      </listitem>
      <listitem>
        <para>
          MEDLEY Encryption Algorithm Specification Rev. 1.0. (IICWG
          SCIP-233.603)
        </para>
      </listitem>
    </itemizedlist>
  </sect2>
  <sect2 id="iso">
    <title>ISO</title>
    <itemizedlist spacing="compact">
      <listitem>
        <para>
          Systems and software engineering -- Architecture description
          (ISO 42010:2011)
        </para>
      </listitem>
      <listitem>
        <para>
          Systems and software engineering -- Architecture Processes
          (ISO CD42020:2016)
        </para>
      </listitem>
    </itemizedlist>
  </sect2>
  <sect2 id="isoiec">
    <title>ISO/IEC</title>
    <itemizedlist spacing="compact">
      <listitem>
        <para>
          Biometric data interchange formats -- Part 14: DNA Data
          (ISO/IEC 19794-6:2013)
        </para>
      </listitem>
      <listitem>
        <para>
          Open Document Format for Office Applications (OpenDocument)
          v1.2 -- Part 1: OpenDocument Schema (ISO/IEC
          26300-1:2015:2015)
        </para>
      </listitem>
      <listitem>
        <para>
          Open Document Format for Office Applications (OpenDocument)
          v1.2 -- Part 2: Recalculated Formula (OpenFormula) Format
          (ISO/IEC 26300-2:2015:2015)
        </para>
      </listitem>
      <listitem>
        <para>
          Open Document Format for Office Applications (OpenDocument)
          v1.2 -- Part 3: Packages (ISO/IEC 26300-3:2015:2015)
        </para>
      </listitem>
    </itemizedlist>
  </sect2>
  <sect2 id="microsoft">
    <title>Microsoft</title>
    <itemizedlist spacing="compact">
      <listitem>
        <para>
          Rich Text Format (RTF) Specification, Version 1.9.1 (Microsoft
          RTF 1.9.1:2008)
        </para>
      </listitem>
    </itemizedlist>
  </sect2>
  <sect2 id="nato">
    <title>NATO</title>
    <itemizedlist spacing="compact">
      <listitem>
        <para>
          NII Communications Reference Architecture Edition 1, Version
          1.2 (NATO AC/322-D(2010)0035)
        </para>
      </listitem>
      <listitem>
        <para>
          Allied Call Sign and Address Group System - Instructions and
          Assignments, NATO Supplement-1 (NATO ACP 100 NS-1(P))
        </para>
      </listitem>
      <listitem>
        <para>
          Allied Call Sign and Address Group System - Instructions and
          Assignments, NATO Supplement-1 (NATO ACP 100 NS-1(Q))
        </para>
      </listitem>
      <listitem>
        <para>
          Address Groups and Call Signs, Instructions and Assignments,
          NATO Supplement-2 (NATO ACP 100 NS-2(A))
        </para>
      </listitem>
      <listitem>
        <para>
          NATO Routing Indicator Book, NATO Supplement-1 (NATO ACP 117
          NS-1 (S))
        </para>
      </listitem>
      <listitem>
        <para>
          NATO Routing Indicator Book, NATO Supplement-1 (NATO ACP 117
          NS-1 (T))
        </para>
      </listitem>
      <listitem>
        <para>
          NATO Subject Indicator System (NASIS), NATO Supplement-2 (NATO
          ACP 117 NS-2 (B))
        </para>
      </listitem>
      <listitem>
        <para>
          NATO Subject Indicator System (NASIS), NATO Supplement-2 (NATO
          ACP 117 NS-2 (C) )
        </para>
      </listitem>
      <listitem>
        <para>
          Handling of ATOMAL Information Within Classified
          Communications Centres, NATO Supplement-2 (NATO ACP 122 NS-2
          (A))
        </para>
      </listitem>
      <listitem>
        <para>
          Handling of ATOMAL Information Within Classified
          Communications Centres, NATO Supplement-2 (NATO ACP 122 NS-2
          (B))
        </para>
      </listitem>
      <listitem>
        <para>
          Policy and Procedures for the Management of IFF/SIF, NATO
          Supplement-1 (NATO ACP 160 NS-1 (F))
        </para>
      </listitem>
      <listitem>
        <para>
          Allied Naval and Maritime Air Communications Instructions,
          NATO Supplement-1 (NATO ACP 176 NS-1 (E))
        </para>
      </listitem>
      <listitem>
        <para>
          Allied Naval and Maritime Air Communications Instructions,
          NATO Supplement-1 (NATO ACP 176 NS-1 (F))
        </para>
      </listitem>
      <listitem>
        <para>
          NATO Guide to Spectrum Management in Military Operations, NATO
          Supplement-1 (NATO ACP 190 NS-1 (C) )
        </para>
      </listitem>
      <listitem>
        <para>
          NATO Guide to Spectrum Management in Military Operations, NATO
          Supplement-2 (NATO ACP 190 NS-2 (C) )
        </para>
      </listitem>
      <listitem>
        <para>
          NATO Guide to Spectrum Management in Military Operations, NATO
          Supplement-2 (NATO ACP 190 NS-2 (D))
        </para>
      </listitem>
      <listitem>
        <para>
          Instructions for the Life Cyle Management of Allied
          Communications Publications (ACPs) - General &amp; NATO Supps
          (NATO ACP 198 NS-1 (G))
        </para>
      </listitem>
      <listitem>
        <para>
          Instructions for the Life Cyle Management of Allied
          Communications Publications (ACPs), NATO Supplement-1 (NATO
          ACP 198 NS-1 (H))
        </para>
      </listitem>
      <listitem>
        <para>
          NINE-Certificate Revocation List Transfer Extension, v.1.0.4
          (NATO NINE-CRL-Transfer)
        </para>
      </listitem>
      <listitem>
        <para>
          NINE-Remote Cryptography Ignition Key Client, v.1.0.4 (NATO
          NINE-Ign-Key-Clt)
        </para>
      </listitem>
      <listitem>
        <para>
          NINE-Remote Cryptography Ignition Key Net Controller, v.1.0.4
          (NATO NINE-Ign-Key-Net Ctrl)
        </para>
      </listitem>
      <listitem>
        <para>
          NINE- IPSec Minimum Essential Interoperability Requirements
          v.1.0.4. (NATO NINE-IPSEC-MER)
        </para>
      </listitem>
      <listitem>
        <para>
          NINE-Traffic Protection Internet Key Exchange version 2 Suite
          A MEDLEY Cryptography, v.1.0.4 (NATO NINE-TP-IKEv2-SA-MED)
        </para>
      </listitem>
      <listitem>
        <para>
          NINE-Traffic Protection Internet Key Exchange version 2 Suite
          A MERCATOR Cryptography, v.1.0.4 (NATO NINE-TP-IKEv2-SA-MER)
        </para>
      </listitem>
      <listitem>
        <para>
          NINE-Traffic Protection Suite A MERCATOR Cryptography, v.1.0.5
          (NATO NINE-TP-SA-MED)
        </para>
      </listitem>
      <listitem>
        <para>
          NINE-Traffic Protection Suite A MEDLEY Cryptography, v.1.0.4
          (NATO NINE-TP-SA-MER)
        </para>
      </listitem>
      <listitem>
        <para>
          NINE-Traffic Protection Suite B Cryptography, v.1.0.4 (NATO
          NINE-TP-SB)
        </para>
      </listitem>
      <listitem>
        <para>
          NINE-Render useless - Zeroization Client, v.1.0.4 (NATO
          NINE-Zero-Net-Clt)
        </para>
      </listitem>
      <listitem>
        <para>
          NINE-Render useless - Zeroization Net Controller, v.1.0.4
          (NATO NINE-Zero-Net-Ctrl)
        </para>
      </listitem>
    </itemizedlist>
  </sect2>
  <sect2 id="nist">
    <title>NIST</title>
    <itemizedlist spacing="compact">
      <listitem>
        <para>
          Secure Hash Standard (NIST FIPS 180-4:2015)
        </para>
      </listitem>
    </itemizedlist>
  </sect2>
  <sect2 id="nso">
    <title>NSO</title>
    <itemizedlist spacing="compact">
      <listitem>
        <para>
          Standard Operating Procedures for Link 1 (NSO ADatP-31
          (C):2009)
        </para>
      </listitem>
      <listitem>
        <para>
          Specifications for Naval Mine Warfare Information and for Data
          Transfer - AMP-11 (Supplement) Edition A (NSO STANAG 1116 Ed
          10:2014)
        </para>
      </listitem>
      <listitem>
        <para>
          NATO Military Oceanographic and Rapid Environmental Assessment
          Support Procedures - ATP-32 Edition E (NSO STANAG 1171 Ed
          10:2016)
        </para>
      </listitem>
      <listitem>
        <para>
          Joint Brevity Words - APP-7 Edition F (NSO STANAG 1401 Ed
          15:2015)
        </para>
      </listitem>
      <listitem>
        <para>
          Warning and Reporting and Hazard Prediction of Chemical,
          Biological, Radiological and Nuclear Incidents (Operators
          Manual) - ATP-45 Edition E (NSO STANAG 2103 Ed 11:2014)
        </para>
      </listitem>
      <listitem>
        <para>
          Digital Interoperability between UHF satellite communications
          terminals (NSO STANAG 4231 Ed 5:2011)
        </para>
      </listitem>
      <listitem>
        <para>
          Super High Frequency (SHF) Military Satellite Communications
          (MILSATCOM) Frequency Division Multiple Access (FDMA) Non-EPM
          Modem for Services Conforming to Class-B Of STANAG 4484 -
          AComP-4486 Edition A (NSO STANAG 4486 Ed 4:2016)
        </para>
      </listitem>
      <listitem>
        <para>
          Advanced SATCOM Network Management and Control (NSO STANAG
          4494 (RD) Ed 1:2010)
        </para>
      </listitem>
      <listitem>
        <para>
          NATO Digital Motion Imagery Standard (- NNSTD MISP-2015.1)
          (NSO STANAG 4609 Ed 4:2016)
        </para>
      </listitem>
      <listitem>
        <para>
          Multi-hop IP Networking with legacy UHF Radios: Mobile ad hoc
          relay Line of Sight Networking (MARLIN) - AComP-4691 Edition A
          (NSO STANAG 4691 Ed 2:2016)
        </para>
      </listitem>
      <listitem>
        <para>
          Standards for Interface of Data Links 1, 11, and 11B Through a
          Buffer - ATDLP-6.01 Edition A (NSO STANAG 5601 Ed 7:2016)
        </para>
      </listitem>
    </itemizedlist>
  </sect2>
  <sect2 id="nso-expected">
    <title>NSO-Expected</title>
    <itemizedlist spacing="compact">
      <listitem>
        <para>
          Super High Frequency (SHF) Medium Data Rate (MDR) Military
          Satellite COMmunications (MILSATCOM) jam-resistant modem
          interoperability standards (NSO-Expected STANAG 4606 Ed 4)
        </para>
      </listitem>
    </itemizedlist>
  </sect2>
  <sect2 id="oasis">
    <title>OASIS</title>
    <itemizedlist spacing="compact">
      <listitem>
        <para>
          Common Alerting Protocol Version 1.2 (OASIS CAP 1.2:2010)
        </para>
      </listitem>
    </itemizedlist>
  </sect2>
  <sect2 id="ogc">
    <title>OGC</title>
    <itemizedlist spacing="compact">
      <listitem>
        <para>
          Web Services Common Implementation Specification v2.0.0 (OGC
          06-121r9:2010)
        </para>
      </listitem>
      <listitem>
        <para>
          Corrigendum 1 for OGC Web Services Common Standard v2.0.0 –
          Multilingual (OGC 11-157:2011)
        </para>
      </listitem>
    </itemizedlist>
  </sect2>
  <sect2 id="omg">
    <title>OMG</title>
    <itemizedlist spacing="compact">
      <listitem>
        <para>
          BPML Business Process Model and Notation version 2.0.2:2014
          (OMG formal/2011-01-03:2014)
        </para>
      </listitem>
      <listitem>
        <para>
          Service Oriented Architecture Modeling Language (SOAML),
          Version 1.0.1 (OMG formal-2012-05-10:2012)
        </para>
      </listitem>
      <listitem>
        <para>
          OMG Systems Modeling Language (OMG SysML) 1.4 (OMG
          formal-2015-06-03:2015)
        </para>
      </listitem>
    </itemizedlist>
  </sect2>
  <sect2 id="sip-forum">
    <title>SIP Forum</title>
    <itemizedlist spacing="compact">
      <listitem>
        <para>
          SIP Connect v.1.1. - Technical Recommendation (2011) (SIP
          Forum SIP Connect v.1.1. )
        </para>
      </listitem>
      <listitem>
        <para>
          SIP Connect v.2.0. - Technical Recommendation (2016/2017) (SIP
          Forum SIP Connect v.2.0. )
        </para>
      </listitem>
    </itemizedlist>
  </sect2>
  <sect2 id="tm-forum">
    <title>TM-FORUM</title>
    <itemizedlist spacing="compact">
      <listitem>
        <para>
          Trouble Ticket REST API Specification R14.5.1 Interface
          (TM-FORUM TMF621:2015)
        </para>
      </listitem>
      <listitem>
        <para>
          Product Ordering API REST Specification R14.5.1 Interface
          (TM-FORUM TMF622:2015)
        </para>
      </listitem>
      <listitem>
        <para>
          API REST Conformance Guidelines R15.5.1 Standard (TM-FORUM
          TR250:2016)
        </para>
      </listitem>
    </itemizedlist>
  </sect2>
  <sect2 id="ws-i">
    <title>WS-I</title>
    <itemizedlist spacing="compact">
      <listitem>
        <para>
          WS-I Basic Profile 1.2 (WS-I BP 1.2:2010)
        </para>
      </listitem>
    </itemizedlist>
  </sect2>
</sect1>


</appendix>
